xd_py_auth/basic_authentication.py
xd_py_auth/conf/config.json
xd_py_auth/mtls.py
xd_py_auth/token_authentication.py
xd_py_auth/xd_auth.pypric
xd_py_auth-0.1.0.dist-info/METADATA
xd_py_auth-0.1.0.dist-info/WHEEL
xd_py_auth-0.1.0.dist-info/RECORD
