Metadata-Version: 2.1
Name: xd_py_auth
Version: 0.1.0
Summary: 
Author: prem reddy
Author-email: prem.reddy@eximietas.design
Requires-Python: >=3.10,<4.0
Classifier: Programming Language :: Python :: 3
Classifier: Programming Language :: Python :: 3.10
Classifier: Programming Language :: Python :: 3.11
Classifier: Programming Language :: Python :: 3.12
Requires-Dist: black (>=24.4.2,<25.0.0)
Requires-Dist: fastapi[all] (>=0.111.0,<0.112.0)
Requires-Dist: freezegun (>=1.5.1,<2.0.0)
Requires-Dist: pytest (>=8.2.2,<9.0.0)
Requires-Dist: python-dotenv (>=1.0.1,<2.0.0)
Requires-Dist: python-jose (>=3.3.0,<4.0.0)
Requires-Dist: uvicorn (>=0.30.1,<0.31.0)
